sphc/__init__.py
sphc/more.py
sphc/test_readme.py
sphc/tests.py
sphc-1.0.1.dist-info/METADATA
sphc-1.0.1.dist-info/WHEEL
sphc-1.0.1.dist-info/top_level.txt
sphc-1.0.1.dist-info/RECORD
