Metadata-Version: 2.4
Name: sphc
Version: 1.0.1
Summary: Simple Pythonic HTML Creator
Author-email: Shekhar Tiwatne <pythonic@gmail.com>
License: MIT
Project-URL: Homepage, https://shon.github.io
Project-URL: Source, https://github.com/shon/sphc
Keywords: html,pythonic,html-generator,web-development
Classifier: Development Status :: 3 - Alpha
Classifier: Intended Audience :: Developers
Classifier: License :: OSI Approved :: MIT License
Classifier: Programming Language :: Python :: 3
Classifier: Topic :: Software Development :: Libraries :: Python Modules
Classifier: Topic :: Text Processing :: Markup :: HTML
Requires-Python: >=3
